expybox/__init__.py
expybox/expybox.py
expybox/explainers/__init__.py
expybox/explainers/anchors.py
expybox/explainers/explainer.py
expybox/explainers/lime.py
expybox/explainers/pdp.py
expybox/explainers/shap.py
expybox/utils/__init__.py
expybox/utils/utils.py
expybox-1.0.1.dist-info/LICENSE.txt
expybox-1.0.1.dist-info/METADATA
expybox-1.0.1.dist-info/WHEEL
expybox-1.0.1.dist-info/top_level.txt
expybox-1.0.1.dist-info/RECORD
